bookscripter/__init__.py
bookscripter-0.1.0.dist-info/entry_points.txt
bookscripter-0.1.0.dist-info/LICENSE
bookscripter-0.1.0.dist-info/WHEEL
bookscripter-0.1.0.dist-info/METADATA
bookscripter-0.1.0.dist-info/RECORD
