Metadata-Version: 2.1
Name: bookscripter
Version: 0.1.0
Summary: Tools for grabbing books from Library Genesis (Libgen).
License: AGPL-3.0
Author: fitzy1293
Author-email: fitzy1293@gmail.com
Requires-Python: >=3.7,<4.0
Classifier: License :: OSI Approved :: GNU Affero General Public License v3
Classifier: Programming Language :: Python :: 3
Classifier: Programming Language :: Python :: 3.7
Classifier: Programming Language :: Python :: 3.8
Classifier: Programming Language :: Python :: 3.9
Requires-Dist: toml (>=0.10.2,<0.11.0)
